quest/__init__.py
quest/contrib/README.md
quest/contrib/__init__.py
quest/contrib/coin.py
quest/contrib/hit_points.py
quest/contrib/inventory.py
quest/contrib/maze_walk_strategy.py
quest/contrib/mouse.py
quest/contrib/npchase.py
quest/contrib/player_enabled.py
quest/contrib/removable.py
quest/contrib/shop.py
quest/contrib/sprite_directionality.py
quest/contrib/submodal.py
quest/contrib/target_strategy.py
quest/contrib/timer.py
quest/dialogue.py
quest/engines.py
quest/errors.py
quest/examples/__init__.py
quest/examples/contrib/__init__.py
quest/examples/contrib/grandma_shop.ink
quest/examples/contrib/hit_points.py
quest/examples/contrib/inventory.py
quest/examples/contrib/maze_walk_strategy.py
quest/examples/contrib/mouse.py
quest/examples/contrib/npchase.py
quest/examples/contrib/player_enabled.py
quest/examples/contrib/shop.py
quest/examples/contrib/shop.txt
quest/examples/contrib/sprite_directionality.py
quest/examples/contrib/timer.py
quest/examples/dialogue_sample.ink
quest/examples/grandma.ink
quest/examples/grandma_variables.ink
quest/examples/grandmas_soup.py
quest/examples/grandmas_soup_variables.py
quest/examples/images/.DS_Store
quest/examples/images/__init__.py
quest/examples/images/box.png
quest/examples/images/boy.png
quest/examples/images/boy_simple.png
quest/examples/images/island/__init__.py
quest/examples/images/island/img_0_0.png
quest/examples/images/island/img_0_1.png
quest/examples/images/island/img_0_10.png
quest/examples/images/island/img_0_11.png
quest/examples/images/island/img_0_12.png
quest/examples/images/island/img_0_13.png
quest/examples/images/island/img_0_14.png
quest/examples/images/island/img_0_15.png
quest/examples/images/island/img_0_2.png
quest/examples/images/island/img_0_3.png
quest/examples/images/island/img_0_4.png
quest/examples/images/island/img_0_5.png
quest/examples/images/island/img_0_6.png
quest/examples/images/island/img_0_7.png
quest/examples/images/island/img_0_8.png
quest/examples/images/island/img_0_9.png
questgame-0.2.2.dist-info/WHEEL
questgame-0.2.2.dist-info/METADATA
questgame-0.2.2.dist-info/RECORD
